setup.py
topattributes/TopAttributes.py
topattributes/__init__.py
topattributes/test.py
topattributes.egg-info/PKG-INFO
topattributes.egg-info/SOURCES.txt
topattributes.egg-info/dependency_links.txt
topattributes.egg-info/not-zip-safe
topattributes.egg-info/top_level.txt