Metadata-Version: 1.0
Name: topattributes
Version: 0.1
Summary: top attributes based on correlation
Home-page: UNKNOWN
Author: UNKNOWN
Author-email: UNKNOWN
License: UNKNOWN
Platform: UNKNOWN
